{"1": {"Usuario": "hola", "Tipo de transacci\u00f3n": "Ingreso", "Fecha": [2024, 10, 8, 16, 27, 39], "Monto": 100.0, "Cuenta origen": "64713537372"}, "2": {"Usuario": "hola", "Tipo de transacci\u00f3n": "Pago de servicio", "Fecha": [2024, 10, 8, 16, 27, 50], "Monto": 40.0, "N\u00famero de factura": "456778"}, "3": {"Usuario": "Tester4", "Tipo de transacci\u00f3n": "Ingreso", "Fecha": [2024, 10, 8, 16, 35, 49], "Monto": 80.0, "Cuenta origen": "81787128196"}, "4": {"Usuario": "Tester4", "Tipo de transacci\u00f3n": "Env\u00edo interno", "Fecha": [2024, 10, 8, 16, 36, 6], "Monto": 30.0, "CVU destino": "64713537372"}}